{
    "chapter": "Gen22",
    "chunk": "002",
    "levenshtein_distance": 2,
    "original_text": "Da stand Abraham des Nachts auf, sattelte seinen Esel, und nahm zwei Knechte und seinen Sohn Isaak mit sich. Und nachdem er Holz zum Brandopfer gespalten, brach er nach dem Orte auf, den Gott ihm bezeichnet hatte.\nAm dritten Tage aber erhob Abraham seine Augen und erblickte den Ort von ferne.",
    "transcribed_text": "Da stand Abraham des nachts auf sattelte seinen Esel und nahm zwei Knechte und seinen Sohn Isaak mit sich und nachdem er Holz zum Brandopfer gespalten brach er nach dem Orte auf den Gott ihm bezeichnet hatte am dritten Tag aber erhob Abraham seine Augen und er blickte den Ort von Ferne"
}