{
    "chapter": "2Chr30",
    "chunk": "006",
    "levenshtein_distance": 19,
    "original_text": "Da gingen die L\u00e4ufer eilig von Stadt zu Stadt durch das Land Ephraim und Manasse bis nach Zabulon hin, doch jene lachten \u00fcber sie und spotteten ihrer.\nEinige M\u00e4nner indes aus Aser und Manasse und Zabulon folgten der Aufforderung und kamen nach Jerusalem.\nAber in Juda wirkte die Hand des Herrn, dass er ihnen Einm\u00fctigkeit verlieh, so dass sie nach dem Gebote des K\u00f6nigs und der F\u00fcrsten das Wort des Herrn erf\u00fcllten.",
    "transcribed_text": "Da gingen die L\u00e4ufer eilig von Stadt zu Stadt durch das Land Ephraim und Manasse bis nach Z Jablonski hin doch jene lachten \u00fcber sie und Sportend ihrer einige M\u00e4nner in des aus Asar und Manas und Zabou folgten der Aufforderung und kamen nach Jerusalem aber in Juda wirkte die Hand des Herrn dass er Ihnen Einm\u00fctigkeit verliehen so dass sie nach dem Gebote des K\u00f6nigs und der F\u00fcrsten das Wort des Herrn erf\u00fcllten"
}