{
    "chapter": "Dtn28",
    "chunk": "012",
    "levenshtein_distance": 5,
    "original_text": "Deine S\u00f6hne und deine T\u00f6chter m\u00f6gen einem andern Volke \u00fcbergeben werden; deine Augen sollen es sehen und m\u00f6gen nach ihrem Anblicke den ganzen Tag schmachten, und deine Hand m\u00f6ge kraftlos sein.\nDie Fr\u00fcchte deines Landes, und alles, was du erarbeitest, m\u00f6ge ein Volk verzehren, das du nicht kennst; und du m\u00f6gest immer Schmach erleiden und unterdr\u00fcckt sein alle Tage,\nund m\u00f6gest au\u00dfer dir sein vor Schrecken \u00fcber die Dinge, die deine Augen sehen werden.",
    "transcribed_text": "Deine S\u00f6hne und deine T\u00f6chter m\u00f6gen einem anderen Volk \u00fcbergeben werden deine Augen sollen es sehen und m\u00f6gen nach ihrem Anblick den ganzen Tag schmachten und deine Hand m\u00f6ge kraftlos sein die Fr\u00fcchte deines Landes und alles was du erarbeitest m\u00f6ge ein Volk verzehren dass du nicht kennst und du m\u00f6gest immer schwach erleiden und unterdr\u00fcckt sein alle Tage und m\u00f6gest au\u00dfer dir sein vor Schrecken \u00fcber die Dinge die deine Augen sehen werden"
}