{
    "chapter": "Dtn34",
    "chunk": "002",
    "levenshtein_distance": 16,
    "original_text": "Und der Herr sprach zu ihm: Dies ist das Land, welches ich Abraham, Isaak und Jakob zugeschworen habe, da ich sprach: Deiner Nachkommenschaft werde ich es geben. Du hast es mit deinen Augen gesehen, aber in dasselbe hin\u00fcberziehen sollst du nicht.\nDa starb Moses, der Knecht des Herrn, daselbst im Lande Moab, nach dem Befehle des Herrn;\nund er begrub ihn im Tale des Landes Moab, Phogor gegen\u00fcber; und kein Mensch kennt seine Grabst\u00e4tte bis auf den gegenw\u00e4rtigen Tag.",
    "transcribed_text": "Und der Herr sprach zu ihm dies ist das Land welches ich Abraham Isaak und Jakob zu geschworen habe da ich sprach deiner Nachkommenschaft werde ich es geben du hast es mit deinen Augen gesehen aber in das selbe hin\u00fcber ziehen sollst du nicht da starb Moses der Knecht des Herrn der selbst im Lande Moab nach dem Befehle des Herrn und der begrub ihn im Tal des Landes Fogo gegen\u00fcber und kein Mensch kennt seine Grabst\u00e4tte bis auf den gegenw\u00e4rtigen Tag"
}