{
    "chapter": "Ps149",
    "chunk": "002",
    "levenshtein_distance": 6,
    "original_text": "Die Heiligen m\u00f6gen frohlocken in Herrlichkeit, sich freuen auf ihren Lagern.\nLobpreisungen Gottes sind in ihrem Munde und zweischneidige Schwerter in ihren H\u00e4nden,\num Rache an den V\u00f6lkern zu vollstrecken, Z\u00fcchtigung an den Nationen;\num ihre K\u00f6nige in Ketten zu werfen, ihre Edlen in eiserne Bande;\num an ihnen das geschriebene Gericht zu vollstrecken. Ruhm ist dies f\u00fcr seine Heiligen! Alleluja!",
    "transcribed_text": "Die heiligen m\u00f6gen frohlocken in Herrlichkeit sich freuen auf ihren Lagern Lobpreisungen Gottes sind in ihrem Munde und zweischneidige Schwerter in ihren H\u00e4nden um Rache an den V\u00f6lkern zu vollstrecken Z\u00fcchtigung an den Nationen um ihre K\u00f6nige in Ketten zu werfen ihre edlen in eiserne Bande wo man ihnen das geschriebene Gericht zu vollstrecken Rom ist dies f\u00fcr seine heiligen Halleluja"
}