{
    "chapter": "Mt27",
    "chunk": "013",
    "levenshtein_distance": 5,
    "original_text": "Die \u00fcbrigen aber sprachen: Halt, wir wollen sehen, ob Elias kommt, ihn zu befreien.\nJesus aber rief wiederum mit lauter Stimme und gab den Geist auf.\nUnd siehe, der Vorhang des Tempels zerriss in zwei St\u00fccke von oben bis unten; und die Erde bebte, und die Felsen spalteten sich,\nund die Gr\u00e4ber \u00f6ffneten sich, und viele Leiber der entschlafenen Heiligen standen auf.",
    "transcribed_text": "Die \u00fcbrigen aber sprachen halt wir wollen sehen ob Elias kommt ihn zu befreien Jesus aber rief wiederum mit lauter Stimme und gab den Geist auf und siehe der Vorhang des Tempels zerrissen in zwei St\u00fccke von oben bis unten und die Erde bebte und die Felsen spaltete sich und die Gr\u00e4ber \u00f6ffneten sich und viele Leiber der entschlafen heiligen standen auf"
}