{
    "chapter": "2Petr2",
    "chunk": "002",
    "levenshtein_distance": 17,
    "original_text": "Hat doch Gott die Engel, welche ges\u00fcndigt hatten, nicht verschont, sondern mit Ketten der H\u00f6lle gefesselt, und sie in den Abgrund zur Peinigung versto\u00dfen, damit sie zum Gerichte aufbewahrt werden,\nund der alten Welt nicht geschont, sondern nur Noe, den Prediger der Gerechtigkeit, als den achten gesch\u00fctzt, als er die S\u00fcndflut \u00fcber die Welt der Gottlosen kommen lie\u00df;\nauch die St\u00e4dte Sodoma und Gomorrha in Asche verwandelt und mit Zerst\u00f6rung bestraft, und sie als Vorbild f\u00fcr die, welche gottlos handeln werden, aufgestellt,\nw\u00e4hrend er den gerechten Lot errettete, der unter der Gewaltt\u00e4tigkeit der Frevler und ihrem ausschweifenden Wandel schwer litt;\ndenn bei allem, was er sah und h\u00f6rte, blieb er gerecht, obwohl er inmitten derer wohnte, welche von Tag zu Tag seine gerechte Seele durch b\u00f6se Werke peinigten.",
    "transcribed_text": "Hat doch Gott die Engel welche ges\u00fcndigt hatten nicht verschont sondern mit Ketten der H\u00f6lle gefesselt und sie in den Abgrund zur Vereinigung versto\u00dfen damit sie zum Gericht aufbewahrt werden und der alten Welt nicht geschont sondern nur nur den Prediger der Gerechtigkeit als den achten gesch\u00fctzt als er die Sintflut \u00fcber die Welt der gottlosen kommen lie\u00df auch die St\u00e4dte so dumm und Gomorrha in Asche verwandelt und mit Zerst\u00f6rung bestraft und sie als Vorbild f\u00fcr die welche gottlos handeln werden aufgestellt w\u00e4hrend er den gerechten Not er rettete der unter der Gewaltt\u00e4tigkeit der Frevler und ihrem ausschweifende Wandel schwer liegt denn bei allem was er sah und h\u00f6rte blieb er gerecht obwohl er in mitten derer wohnte welche von Tag zu Tag seine gerechte Seele durch b\u00f6se Werke peinigten"
}