{
    "chapter": "Apg14",
    "chunk": "002",
    "levenshtein_distance": 8,
    "original_text": "Allein die Volksmenge der Stadt war geteilt; einige hielten es n\u00e4mlich mit den Juden, andere hingegen mit den Aposteln.\nAls aber die Heiden und die Juden mit ihren Vorstehern sich erhoben, um sie zu misshandeln und zu steinigen,\nflohen die Apostel, davon in Kenntnis gesetzt, in die St\u00e4dte von Lykaonien, Lystra und Derbe, und in die ganze Gegend im Umkreise; und dort verk\u00fcndeten sie das Evangelium.",
    "transcribed_text": "Allein die Volksmenge der Stadt war geteilt einige hielten es n\u00e4mlich mit den Juden andere hingegen mit den Aposteln als aber die Heiden und die Juden mit ihren Vorsteher sich erhoben um sie zu misshandeln und zu steinigen flohen die Apostel davon in Kenntnis gesetzt in die St\u00e4dte von Lyon Ian LYSTRA und sterbe und in die ganze Gegend im Umkreis und dort verk\u00fcndeten sie das Evangelium"
}