{
    "chapter": "1Koen6",
    "chunk": "005",
    "levenshtein_distance": 11,
    "original_text": "So baute er das Haus und vollendete es und bedeckte das Haus mit Tafelwerk von Zedern.\nUnd \u00fcber dem ganzen Hause her erbaute er ein Stockwerk, f\u00fcnf Ellen in der H\u00f6he, und deckte das Haus mit Zedernholz.\nDa erging das Wort des Herrn an Salomon und er sprach:\nDu bauest nun dieses Haus; wenn du in meinen Geboten wandelst und nach meinen Rechten tuest und alle meine Gesetze h\u00e4ltst und darnach wandelst, so will ich mein Wort an dir best\u00e4tigen, welches ich zu David, deinem Vater, gesprochen habe.",
    "transcribed_text": "Baute er das Haus und vollendete es und bedeckte das Haus mit Tafelwerk von Zedern und \u00fcber dem ganzen Haus her er baute eher ein Stockwerk f\u00fcnf Ellen in der H\u00f6he und deckte das Haus mit Zedernholz da er ging das Wort des Herrn an Salomon und er sprach du baust nun dieses Haus wenn du in meinen Geboten wandelst und nach meinen rechten tust und alle meine Gesetze h\u00e4ltst und danach wandelst so will ich mein Wort an dir best\u00e4tigen welches ich zu David deinem Vater gesprochen habe"
}