{
    "chapter": "Dtn19",
    "chunk": "002",
    "levenshtein_distance": 18,
    "original_text": "Dies soll die Bestimmung f\u00fcr einen fl\u00fcchtigen Totschl\u00e4ger sein, dessen Leben gesch\u00fctzt werden soll: Wer seinen N\u00e4chsten unversehens erschlagen hat und von wem es erwiesen ist, dass er keinen Hass gegen ihn gehegt habe, weder gestern noch vorher,\nsondern dass er mit ihm arglos in den Wald gegangen ist, um Holz zu f\u00e4llen, und dass die Axt bei dem F\u00e4llen der B\u00e4ume seiner Hand entfuhr, und das Eisen aus dem Stiele glitt, und seinen Freund traf und t\u00f6tete, ein solcher soll in eine der vorgenannten St\u00e4dte fliehen und am Leben bleiben;\ndamit nicht etwa der n\u00e4chste Verwandte desjenigen, dessen Blut vergossen worden ist, durch seinen Schmerz gereizt, ihn verfolge und ihn, wenn der Weg weit w\u00e4re, einhole und erschlage, obwohl er doch des Todes nicht schuldig ist, weil er erweislich vordem gegen den Get\u00f6teten keinen Hass gehegt hat.",
    "transcribed_text": "Dies soll die Bestimmung f\u00fcr einen fl\u00fcchtigen Totschl\u00e4ger sein dessen Leben gesch\u00fctzt werden soll wer seine n\u00e4chsten unversehens erschlagen hat und von wem ist erwiesen ist dass er keinen Hass gegen ihn gehegt habe weder gestern noch vorher sondern dass er mit ihm arglos in den Wald gegangen ist um Holz zu f\u00e4llen und dass die Axt bei dem f\u00e4llen der B\u00e4ume seiner Hand fuhr und das Eisen aus dem Stieglitz und seinen Freund traf und t\u00f6tete ein solcher soll in eine der vorgenannten St\u00e4dte fliehen und am Leben bleiben damit nicht etwa der n\u00e4chste Verwandte desjenigen dessen Blut vergossen worden ist durch seinen Schmerz gereizt ihn verfolge und ihn wenn der Weg weit w\u00e4re einhole und er schlage obwohl er doch des Todes nicht schuldig ist weil er erweist sich vor denen gegen den get\u00f6teten keinen Hass gehegt hat"
}