{
    "chapter": "1Petr2",
    "chunk": "002",
    "levenshtein_distance": 7,
    "original_text": "Darum steht in der Schrift: Siehe, ich lege in Sion einen auserlesenen kostbaren Eckstein; und wer an ihn glaubt, wird nicht zu Schanden werden.\nEuer also, die ihr glaubt, ist die Ehre, denen aber, die nicht glauben, ist der Stein, den die Bauleute verworfen haben, der ist zum Eckstein geworden,\nund zum Stein des Ansto\u00dfes und zum Fels des \u00c4rgernisses denen, welche Ansto\u00df an dem Worte nehmen, und an dasselbe nicht glauben, wozu sie auch bestimmt sind.",
    "transcribed_text": "Darum steht in der Schrift siehe ich lege in Zion einen aus erlesenen kostbaren Eckstein und wer an ihn glaubt wird nicht zu Schande werden euer also die ihr glaubt es die Ehre denen aber die nicht glauben ist der Stein den die Bauleute verworfen haben der ist zum Eckstein geworden und zum Stein des Ansto\u00dfes und zum Feld des \u00c4rgernisses denen welche Ansto\u00df an dem Worte nehmen und an das selbe nicht glauben wozu sie auch bestimmt sind"
}