{
    "chapter": "Joel1",
    "chunk": "003",
    "levenshtein_distance": 10,
    "original_text": "Wehklage wie eine Jungfrau, die ein Trauergewand angelegt hat, um den Mann ihrer Jugend.\nEntschwunden sind Speis- und Trankopfer vom Hause des Herrn, es trauern die Priester, die Diener des Herrn.\nVerw\u00fcstet ist das Gefilde, es trauert das Feld, denn vernichtet ist der Weizen, verdorrt der Wein, verschmachtet das \u00d6l.",
    "transcribed_text": "Weg Klage wie eine Jungfrau die ein Trauergewand angelegt hat um den Mann ihrer Jugend entschwunden sind Speis und trank Opfer vom Hause des Herrn ist trauern die Priester die Diener des Herrn verw\u00fcstet ist das Gefilte es trauert das Feld denn vernichtet ist der Weizen Fedora der Wein verschmachtet das \u00d6l"
}