{
    "chapter": "Gen14",
    "chunk": "003",
    "levenshtein_distance": 52,
    "original_text": "Und sie wandten sich und kamen zu der Quelle Misphat, das ist Kades, und schlugen das ganze Land der Amalekiter und die Amorrhiter, welche in Asasonthamar wohnten.\nDa zogen der K\u00f6nig von Sodoma, und der K\u00f6nig von Gomorrha, und der K\u00f6nig von Adama, und der K\u00f6nig von Seboim, und der K\u00f6nig von Bala, das ist Segor, aus und stellten sich im Waldtale in Schlachtordnung gegen sie auf:\nn\u00e4mlich gegen Chodorlahomor, den K\u00f6nig der Elamiter, und Thadal, den K\u00f6nig der V\u00f6lker, und Amraphel, den K\u00f6nig von Sennaar, und Arioch, den K\u00f6nig von Pontus, vier K\u00f6nige gegen f\u00fcnf.",
    "transcribed_text": "Und sie wandern sich und kamen zu der Quelle Miss Fart das ist Charades und schlugen das ganze Land der AmaLee Kita und die Amoriter welche in Asiant wohnten da zogen der K\u00f6nig von Sodom und der K\u00f6nig von Gomorrha und der K\u00f6nig von Adam und der K\u00f6nig von Sebo ihm und der K\u00f6nig von Balla das ist Segor aus und stellten sich im Waldhalle in Schlacht Ordnung gegen sie auf n\u00e4mlich gegen Cordula Humor den K\u00f6nig der Elam Mieter und Tadal den K\u00f6nig der V\u00f6lker und am Rafael den K\u00f6nig von Senna und Ari den K\u00f6nig von Ponto vier K\u00f6nige gegen f\u00fcnf"
}