{
    "chapter": "Jer38",
    "chunk": "007",
    "levenshtein_distance": 8,
    "original_text": "Hiernach sandte der K\u00f6nig Sedekias und lie\u00df den Propheten Jeremias zu sich holen an den dritten Eingang am Hause des Herrn. Und der K\u00f6nig sprach zu Jeremias: Ich will dich etwas fragen, verhehle mir nichts!\nJeremias aber sprach zu Sedekias: Wenn ich es dir kundtue, wirst du mich dann nicht t\u00f6ten? Und wenn ich dir einen Rat erteile, wirst du nicht auf mich h\u00f6ren.",
    "transcribed_text": "Hier nach sandte der K\u00f6nigsee Kias und lie\u00df den Propheten Jeremias zu sich holen an den dritten Eingang am Hause des Herrn und der K\u00f6nig sprach zu Jeremias ich will dich etwas fragen verhehle mir nichts Jeremias aber sprach zu Sedia wenn ich es dir kund tue wirst du mich dann nicht t\u00f6ten und wenn ich dir einen Rat erteile wirst du nicht auf mich h\u00f6ren"
}