{
    "chapter": "Jos22",
    "chunk": "001",
    "levenshtein_distance": 14,
    "original_text": "Zu derselben Zeit rief Josue die Rubeniter, die Gaditer, und den halben Stamm Manasse,\nund sprach zu ihnen: Ihr habt alles getan, was euch Moses, der Diener des Herrn, geboten hat; und auch mir seid ihr in allem gehorsam gewesen\nund habt eure Br\u00fcder diese lange Zeit hindurch, bis auf den heutigen Tag, nicht verlassen, und das Gebot des Herrn, eures Gottes, treu beobachtet.",
    "transcribed_text": "Zu der selben Zeit rief Joshua die Ruiter die Ganita und den halben Stamm nasse und sprach zu Ihnen ihr habt alles getan was euch Moses der Diener des Herren geboten hat und auch mir seid ihr in allem Gehorsam gewesen und habt eure Br\u00fcder diese lange Zeiten hindurch bis auf den heutigen Tag nicht verlassen und das Gebot des Herrn eures Gottes treu beobachtet"
}