{
    "chapter": "Ijob18",
    "chunk": "005",
    "levenshtein_distance": 5,
    "original_text": "Ob seines Gerichtstages werden die Sp\u00e4teren sich entsetzen und Schrecken wird die Fr\u00fcheren \u00fcberfallen.\nDas f\u00fcrwahr sind die Wohnungen der Gottlosen und das ist die St\u00e4tte desjenigen, der Gott nicht kennen will.",
    "transcribed_text": "Ob seines Gerichtstag werden die sp\u00e4teren sich Entsetzen und Schrecken wird die fr\u00fcheren \u00fcberfallen das f\u00fcr wahr sind die Wohnungen der gottlosen und das ist die St\u00e4dte des jenigen der Gott nicht kennen will"
}