{
    "chapter": "Mi2",
    "chunk": "003",
    "levenshtein_distance": 3,
    "original_text": "Sprechet doch nicht, sagen sie. Es soll nicht Weissagung \u00fcber sie ergehen, nicht wird sie die Schmach treffen.\nEs spricht das Haus Jakob: Ist denn des Herrn Geist verk\u00fcrzt oder sind dies seine Gedanken? Sind meine Worte nicht g\u00fctig gegen den, der gerecht wandelt?\nMein Volk dagegen hat sich als Feind erhoben, vom Gewande habt ihr den Mantel weggerissen und die, welche arglos dahinziehen, habt ihr in Streit verwickelt.",
    "transcribed_text": "Spreche doch nicht sagen Sie es soll nicht Weissagung \u00fcber sie ergehen nicht wird sie die Schmach treffen es spricht das Haus Jakob ist denn des Herrn Geist verk\u00fcrzt oder sind dies seine Gedanken sind meine Worte nicht g\u00fcltig gegen den der gerecht wandelt mein Volk dagegen hat sich als Feind erhoben vom Gewande habt ihr den Mantel weggerissen und die welche arglos da hinziehen habt ihr in Streit verwickelt"
}