{
    "chapter": "Ps9",
    "chunk": "004",
    "levenshtein_distance": 15,
    "original_text": "Erbarme dich meiner, Herr! siehe meine Erniedrigung durch meine Feinde,\nder du mich emporhebst aus den Toren des Todes, auf dass ich deine Ruhmestaten verk\u00fcnde an den Toren der Tochter Sion.\nIch will frohlocken ob deines Heiles. Dahingesunken sind die Heiden ins Verderben, das sie mir bereiteten. In dem Fallstricke, den sie heimlich gelegt, verwickelte sich ihr eigener Fu\u00df.",
    "transcribed_text": "Erbarme dich meiner Herr siehe meine Erniedrigung durch meine Feinde der du mich empor hebst aus den Toren des Todes auf dass ich deine Room Daten verk\u00fcnde an den Toren der Tochter Sieren ich will frohlocken ob dein heiles Da gesunken sind die Heiden ins verderben dass sie mir bereiteten in dem Fallstricke den sie heimlich gelegt verwickelte sich ihr eigener Fu\u00df"
}