{
    "chapter": "Ps9",
    "chunk": "007",
    "levenshtein_distance": 36,
    "original_text": "(3.) Denn der S\u00fcnder r\u00fchmt sich ob der Gel\u00fcste seiner Seele und der Frevler segnet sich.\n(4.) Der S\u00fcnder erbittert den Herrn und wegen seines gro\u00dfen Zornes fr\u00e4gt er nichts nach ihm.\n(5.) Gott steht ihm nicht vor Augen, seine Wege sind befleckt zu jeder Zeit. Deine Gerichte sind seinem Blicke entr\u00fcckt, alle seine Feinde knechtet er.",
    "transcribed_text": "Dritter denn der S\u00fcnder r\u00fchrt sich ob der Gel\u00fcste seiner Seele und der Frevler segnet sich vierter der S\u00fcnder erbittert den Herrn und wegen seines gro\u00dfen Zorns fr\u00e4gt er nichts nach ihm er Ustream f\u00fcnfter Gott steht ihm nicht vor Augen seine Wege sind befleckt zu jederzeit Deine Gerichte sind seine Blicke entr\u00fcckt alle seine Feinde Knechte er"
}