{
    "chapter": "Jdt11",
    "chunk": "007",
    "levenshtein_distance": 14,
    "original_text": "Und weil Gott \u00fcber sie erz\u00fcrnt ist, bin ich gesandt worden, dir eben dies kundzutun.\nAlle diese Worte aber gefielen dem Holofernes und seinen Dienern und sie verwunderten sich \u00fcber ihre Weisheit und einer sprach zu dem andern:\nDieser Frau ist keine auf Erden gleich an Gestalt und Sch\u00f6nheit und Weisheit der Reden.",
    "transcribed_text": "Und bei Gott \u00fcber sie erziehend ist bin ich gesandt worden dir eben dies kund zu tun alle diese Worte aber gefiel dem Holofernes und seinen Dienern und sie verwundert sich \u00fcber ihre Weisheit und einer sprach zu dem andern dieser Frau ist keiner auf Erden gleich an Gestalt und Sch\u00f6nheit und Weisheit der Reden"
}