{
    "chapter": "Ex11",
    "chunk": "001",
    "levenshtein_distance": 5,
    "original_text": "Und der Herr sprach zu Moses: Noch mit einer Plage will ich Pharao und \u00c4gypten schlagen, alsdann wird er euch ziehen lassen, ja euch dr\u00e4ngen, wegzuziehen.\nSage daher dem ganzen Volke, dass die M\u00e4nner von ihren Freunden, und die Weiber von ihren Nachbarinnen silberne und goldene Gef\u00e4\u00dfe fordern.\nDer Herr aber wird sein Volk Gnade bei den \u00c4gyptern finden lassen. Auch war Moses ein sehr angesehener Mann im Lande \u00c4gypten, bei den Dienern Pharaos und bei dem ganzen Volke.",
    "transcribed_text": "Und der Herr sprach zu Moses noch mit einer Plage will ich Faro und \u00c4gypten schlagen als dann wird er euch ziehen lassen ja euch dr\u00e4ngen wegzuziehen sage daher dem ganzen Volke dass die M\u00e4nner von ihren Freunden und die Weiber von ihren Nachbarinnen silberne und goldene Gef\u00e4\u00dfe fordern der Herr aber wird sein Volk Gnade bei den \u00c4gyptern finden lassen auch war Moses ein sehr angesehener Mann im Lande \u00c4gypten bei den Dienern Pharaos und bei dem ganzen Volker"
}