{
    "chapter": "Offb6",
    "chunk": "006",
    "levenshtein_distance": 16,
    "original_text": "Und der Himmel wich zur\u00fcck wie ein Buch, das man zusammenrollt, und alle Berge und Inseln wurden von ihrer St\u00e4tte ger\u00fcckt.\nUnd die K\u00f6nige der Erde, und die F\u00fcrsten, und die Heerf\u00fchrer, und die Reichen, und die M\u00e4chtigen, und alle Knechte und alle Freien verbargen sich in die H\u00f6hlen und in die Felsen der Berge,\nund sie sprechen zu den Bergen und den Felsen: Fallet \u00fcber uns, und bedecket uns vor dem Angesichte dessen, der auf dem Throne sitzt, und vor dem Zorne des Lammes!\nDenn gekommen ist der gro\u00dfe Tag ihres Zornes; und wer wird bestehen k\u00f6nnen?",
    "transcribed_text": "Und der Himmel w\u00e4chst zur\u00fcck wie ein Buch das man zusammen rollt und alle Berge und Inseln wurden von ihrer St\u00e4dte ger\u00fcckt und die K\u00f6nige der Erde und die F\u00fcrsten und die Her F\u00fchrer und die Reichen und die m\u00e4chtigen und alle Knechte und alle freien verborgen sich in die H\u00f6hen und in die Felsen der Berge und sie sprechen zu den Bergen und den Felsen fallen \u00fcber uns und bedeckt uns vor dem Angesicht dessen der auf dem Throne sitzt und vor dem Z Corner des Lammes Denn gekommen ist der gro\u00dfe Tag ihres Zorns und wer wird bestehen k\u00f6nnen"
}