{
    "chapter": "1Sam26",
    "chunk": "007",
    "levenshtein_distance": 7,
    "original_text": "Da sprach Saul: Ich habe ges\u00fcndigt, kehre zur\u00fcck, mein Sohn David! denn ich werde dir fortan nichts mehr zuleide tun, darum dass heute mein Leben in deinen Augen kostbar gewesen ist; denn es zeigt sich, dass ich t\u00f6richt gehandelt habe und gar vieles nicht wusste.\nDavid antwortete und sprach: Siehe, hier ist der Speer des K\u00f6nigs; einer von den Dienern des K\u00f6nigs m\u00f6ge her\u00fcberkommen und ihn holen.",
    "transcribed_text": "Der sprach Saul ich habe ges\u00fcndigt kehre zur\u00fcck mein Sohn David denn ich werde dir sofort an nichts mehr zu leide tun darum dass heute mein Leben in deinen Augen kostbar gewesen ist denn es zeigt sich dass ich t\u00f6richt gehandelt habe und gar vieles nicht wusste David antwortete und sprach siehe hier ist der Speer des K\u00f6nigs einer von den Dienern des K\u00f6nigs m\u00f6ge her\u00fcber kommen und ihn holen"
}