{
    "chapter": "Gen17",
    "chunk": "002",
    "levenshtein_distance": 7,
    "original_text": "Und Gott sprach zu ihm: Ich bin es, und mein Bund ist mit dir, und du sollst der Stammvater vieler V\u00f6lker werden.\nFortan sollst du nicht Abram hei\u00dfen, sondern Abraham soll dein Name sein; denn ich habe dich zum Stammvater vieler V\u00f6lker bestimmt.\nUnd ich will machen, dass deine Nachkommen sich mehren \u00fcber die Ma\u00dfen und zu V\u00f6lkern anwachsen, und K\u00f6nige sollen von dir abstammen.",
    "transcribed_text": "Und Gott sprach zu ihm ich bin es und mein Bund ist mit dir und du sollst der Stammvater viel V\u00f6lker werden fort an sollst du nicht Abraham hei\u00dfen sondern Abraham soll dein Name sein denn ich habe dich zum Stammvater viel V\u00f6lker bestimmt und ich will machen dass deine Nachkommen sich mehren \u00fcber die Ma\u00dfen und zu V\u00f6lkern anwachsen und K\u00f6nige sollen von dir abstammen"
}