{
    "chapter": "Joh6",
    "chunk": "001",
    "levenshtein_distance": 14,
    "original_text": "Hiernach fuhr Jesus \u00fcber das Meer von Galil\u00e4a, das ist von Tiberias.\nUnd es folgte ihm eine gro\u00dfe Menge Volkes nach, weil sie die Wunder sahen, welche er an den Kranken tat.\nDa ging Jesus auf den Berg, und setzte sich daselbst mit seinen J\u00fcngern nieder.\nEs war aber das Osterfest der Juden nahe.",
    "transcribed_text": "Hier nach vor Jesus \u00fcber das Meer von Galilei das ist von Tiberias und es folgte ihm eine gro\u00dfe Menge Volkes nach weil sie die Wunders sahen welche er an den Crankdat da ging Jesus auf den Berg und setzte sich da selbst mit seinen J\u00fcnger nieder es war aber das Osterfest der Juden nahe"
}