{
    "chapter": "Ps72",
    "chunk": "003",
    "levenshtein_distance": 3,
    "original_text": "Sie erheben ihren Mund in den Himmel und ihre Zunge wandelt auf der Erde.\nDarum wendet sich mein Volk dorthin, denn gute Tage finden sich bei ihnen.\nSie sprechen: Wie sollte Gott es wissen und g\u00e4be es Wissen bei dem H\u00f6chsten?\nSiehe, sie sind S\u00fcnder und haben doch \u00dcberfluss in der Welt, haben Reicht\u00fcmer erlangt.",
    "transcribed_text": "Sie erheben ihren Mund in den Himmel und ihre Zunge wandelt auf der Erde darum wendet sich mein Volk dorthin denn gute Tage finden sich bei Ihnen Sie sprechen wie sollte Gottes wissen und g\u00e4be es wissen bei dem h\u00f6chsten sie sie sind S\u00fcnder und haben doch \u00dcberfluss in der Welt haben Reicht\u00fcmer erlangt"
}