{
    "chapter": "Mt28",
    "chunk": "001",
    "levenshtein_distance": 15,
    "original_text": "Nach Ablauf des Sabbates aber, als der Morgen am ersten Tage der Woche anbrach, kam Maria Magdalena und die andere Maria, das Grab zu schauen.\nUnd siehe, ein gro\u00dfes Erdbeben entstand, denn ein Engel des Herrn stieg vom Himmel herab, trat hinzu, w\u00e4lzte den Stein hinweg, und setzte sich darauf.",
    "transcribed_text": "Nach Ablauf des Sabbat es aber als der Morgen am ersten Tage der Woche an der Woche an brach kam Maria Magdalena und die andere Maria das Grab zu schauen und siehe ein gro\u00dfes Erdbeben entstand denn ein Engel des Herrn stieg vom Himmel herab trat hinzu w\u00e4lzte den Stein hinweg und setzte sich darauf"
}