{
    "chapter": "Klgl1",
    "chunk": "011",
    "levenshtein_distance": 9,
    "original_text": "Sie h\u00f6ren, wie ich seufze, doch niemand wird mein Tr\u00f6ster; alle meine Feinde h\u00f6ren von meinem Ungl\u00fcck, sie freuen sich, dass du es getan; doch du bringst den Tag des Trostes herbei und sie sollen werden wie ich. Thau.\nM\u00f6ge all ihre Bosheit vor dein Angesicht gelangen und halte du Weinlese an ihnen, wie du an mir Lese gehalten ob aller meiner Verschuldungen, denn meine Seufzer sind viel und mein Herz ist siech.",
    "transcribed_text": "Sie h\u00f6ren wie ich seufzte doch niemand wird mein Tr\u00f6ster alle meine Feinde h\u00f6ren von meinem Ungl\u00fcck sie freuen sich dass du es getan doch du bringst den Tag des Trostes herbei und sie sollen werden wie ich Tau m\u00f6ge all ihre Bosheit vor dein Angesicht gelangen und halte du Wein Leser an ihnen wie du an mir lese gehalten ob all meiner Verschuldung denn meine Seufzer sind viel und mein Herz ist sich"
}