{
    "chapter": "Ri12",
    "chunk": "001",
    "levenshtein_distance": 46,
    "original_text": "Aber siehe, ein Aufstand erhob sich in Ephraim; es zogen n\u00e4mlich M\u00e4nner nach Norden und sprachen zu Jephte: Warum bist du in den Kampf gegen die S\u00f6hne Ammons gezogen und hast uns nicht gerufen, damit wir mit dir zogen? Jetzt werden wir daf\u00fcr dein Haus anz\u00fcnden.\nEr antwortete ihnen: Ich und mein Volk hatten einen heftigen Streit mit den S\u00f6hnen Ammons; da rief ich euch, mir zu Hilfe zu kommen, aber ihr habt es nicht tun wollen.",
    "transcribed_text": "Hier ist der Text Read a laut for You aber siehe ein Aufstand erhob sich in Efraim es zogen n\u00e4mlich M\u00e4nner nach Norden und sprachen zu Jeff VTE warum bist du in den Kampf gegen die S\u00f6hne Amons gezogen und hast uns nicht gerufen damit wir mit dir zogen jetzt werden wir daf\u00fcr dein Haus anz\u00fcnden er antwortete Ihnen ich und mein Volk hatten einen heftigen Streit mit den S\u00f6hnen Amons da rief ich euch mir zu Hilfe zu kommen aber ihr habt es nicht tun wollen"
}