{
    "chapter": "Dan9",
    "chunk": "005",
    "levenshtein_distance": 5,
    "original_text": "Ganz Israel hat dein Gesetz \u00fcbertreten und ist abgefallen, so dass sie nicht auf deine Stimme h\u00f6rten; darum ergoss sich \u00fcber uns der Fluch und Schwur, der im Buche Moses, des Dieners Gottes, geschrieben steht, denn wir haben wider Ihn ges\u00fcndigt.\nEr hat sein Wort, das er wider uns und wider unsere F\u00fcrsten, die unsere Richter waren, gesprochen, erf\u00fcllt, dass er dies gro\u00dfe Ungl\u00fcck \u00fcber uns brachte, wie ein solches unter dem ganzen Himmel niemals gewesen, wie es an Jerusalem geschehen.",
    "transcribed_text": "Ganz Israel hat dein Gesetz \u00fcbertreten und ist abgefallen so dass sie nicht auf deine Stimme h\u00f6rten darum ergoss sich \u00fcber uns der Fluch und Schwur der im Buche Moses des Diener Gottes geschrieben steht denn wir haben wieder ihn ges\u00fcndigt er hat sein Wort dass er wieder uns und wieder unsere F\u00fcrsten die unsere Richter waren gesprochen erf\u00fcllt dass er dies gro\u00dfe Ungl\u00fcck \u00fcber uns brachte wie ein solches unter dem ganzen Himmel niemals gewesen wie es an Jerusalem geschehen"
}