{
    "chapter": "Tob10",
    "chunk": "001",
    "levenshtein_distance": 4,
    "original_text": "Als aber Tobias der Hochzeit wegen s\u00e4umte, ward sein Vater Tobias besorgt und sprach: Warum s\u00e4umt mein Sohn wohl, oder warum h\u00e4lt man ihn dort zur\u00fcck?\nIst Gabel vielleicht gestorben, dass ihm niemand das Geld zur\u00fcckgibt?\nUnd er fing an, sich sehr zu betr\u00fcben, und Anna, sein Weib, mit ihm, und beide fingen an, miteinander zu weinen, weil ihr Sohn an dem bestimmten Tag nicht wieder zu ihnen zur\u00fcckkehrte.",
    "transcribed_text": "Als aber Tobias der Hochzeit wegen s\u00e4umte war sein Vater Tobias besorgt und sprach warum s\u00e4umt mein Sohn wohl oder warum h\u00e4lt man ihn dort zur\u00fcck ist Gabel vielleicht gestorben dass ihm niemand das Geld zur\u00fcck gibt und er fing an sich sehr zu betr\u00fcgen und Anna sein Weib mit ihm und beide fingen an miteinander zu weinen weil ihr Sohn an dem bestimmten Tag nicht wieder zu Ihnen zur\u00fcckkehrt"
}