{
    "chapter": "Ex17",
    "chunk": "003",
    "levenshtein_distance": 17,
    "original_text": "Und er nannte den Namen dieses Ortes Versuchung wegen des Haderns der S\u00f6hne Israels, und weil sie den Herrn versuchten und sprachen: Ist der Herr in unserer Mitte, oder nicht?\nDa kam aber Amalek heran und stritt mit Israel in Raphidim.\nUnd Moses sprach zu Josue: W\u00e4hle M\u00e4nner aus, und ziehe hin, k\u00e4mpfe mit Amalek; ich aber will morgen auf dem Gipfel des H\u00fcgels stehen, den Stab Gottes in meiner Hand.",
    "transcribed_text": "Und er nannte den Namen dieses Ortes Versuchung wegen des Harders der S\u00f6hne Israels und weil sie den Herrn versuchten und Sprachen ist der Herr in unserer Mitte oder nicht da kam aber Ale heran und tritt mit Israel in Ravid und Moses sprach zu Joshua w\u00e4hle M\u00e4nner aus und siehe hin k\u00e4mpfe mit Amalric ich aber will morgen auf dem Gipfel des H\u00fcgelsstehen den Stab Gottes in meiner Hand"
}