{
    "chapter": "Ez11",
    "chunk": "002",
    "levenshtein_distance": 8,
    "original_text": "Darum weissage \u00fcber sie, weissage, Menschensohn!\nAlsbald kam auf mich der Geist des Herrn und sprach zu mir: Verk\u00fcnde: So spricht der Herr: So habt ihr geredet, Haus Israel! und die Gedanken eures Herzens kenne ich.\nIhr habt sehr viele in dieser Stadt get\u00f6tet und deren Stra\u00dfen mit Erschlagenen angef\u00fcllt.",
    "transcribed_text": "Darum weissage \u00fcber sie weissage Menschensohn als bald kam auf mich der Geist des Herrn und sprach zu mir f\u00fcr Kunde so spricht der Herr so habt ihr geredet aus Israel und die Gedanken eures Herzens kenne ich ihr habt sehr viele in dieser Stadt get\u00f6tet und deren Stra\u00dfen mit erschlagen angef\u00fcllt"
}