{
    "chapter": "1Sam9",
    "chunk": "011",
    "levenshtein_distance": 7,
    "original_text": "Und Samuel sprach zum Koche: Gib das St\u00fcck her, das ich dir gegeben habe, mit der Weisung, du sollest es besonders bei dir aufheben!\nDa trug der Koch das Schulterst\u00fcck auf und setzte es Saul vor. Und Samuel sprach: Siehe da, was noch \u00fcbrig geblieben ist! Lege es vor dich und iss; denn mit Flei\u00df ward es f\u00fcr dich aufbehalten, als ich das Volk rief. Und Saul a\u00df mit Samuel an jenem Tage.",
    "transcribed_text": "Und Samuel sprach zum Kochen gib das St\u00fcck her dass ich dir gegeben habe mit der Weisung du solltest es besonders bei dir aufheben da trug der Koch das Schulter St\u00fcck auf und setzte es Saul vor und Samuel sprach siehe da was noch \u00fcbrig geblieben ist lege es vor dich und ist dann mit Flei\u00df war es f\u00fcr dich aufbehalten als ich das Volk rief und Saul a\u00df mit Samuel an jenem Tage"
}