{
    "chapter": "Mt18",
    "chunk": "006",
    "levenshtein_distance": 1,
    "original_text": "Wenn er auch auf diese nicht h\u00f6rt, so sage es der Kirche; wenn er aber auf die Kirche nicht h\u00f6rt, so sei er dir wie der Heide und der Z\u00f6llner.\nWahrlich, ich sage euch, was ihr immer auf Erden binden werdet, wird auch im Himmel gebunden sein; und was ihr immer auf Erden l\u00f6sen werdet, wird auch im Himmel gel\u00f6st sein!\nAbermals sage ich euch: Wenn zwei aus euch auf Erden eines Sinnes sein werden \u00fcber was immer f\u00fcr eine Sache, um die sie bitten wollen, so wird sie ihnen von meinem Vater, der im Himmel ist, zuteil werden.",
    "transcribed_text": "Wenn er auch auf diese nicht h\u00f6rt so sage es der Kirche wenn er aber auf die Kirche nicht h\u00f6rt so sei er dir wie der Heide und der Z\u00f6llner wahrlich ich sage euch was ihr immer auf Erden binden werdet wird auch im Himmel gebunden sein und was ihr immer auf Erden l\u00f6sen werdet wird auch im Himmel gel\u00f6st sein Abermals sage ich euch wenn zwei aus euch auf Erden eines sinnes sein werden \u00fcber was immer f\u00fcr eine Sache um die sie bitten wollen so wird sie Ihnen von meinem Vater der im Himmel ist zu Teil werden"
}