{
    "chapter": "Dtn20",
    "chunk": "001",
    "levenshtein_distance": 15,
    "original_text": "Wenn du gegen deine Feinde zum Kriege ausziehst und siehst Reiter und Wagen, und ein gr\u00f6\u00dferes feindliches Kriegsvolk, als du hast, so f\u00fcrchte dich nicht vor ihnen; denn der Herr, dein Gott, der dich aus dem Lande \u00c4gypten gef\u00fchrt hat, ist mit dir.\nWenn aber die Schlacht nahe bevorsteht, so soll der Priester vor das Heer treten und also zum Volke sprechen:\nH\u00f6re, Israel! ihr liefert heute eine Schlacht gegen eure Feinde, euer Herz verzage nicht, f\u00fcrchtet euch nicht, weichet nicht, und erschrecket nicht vor ihnen;\ndenn der Herr, euer Gott, ist in eurer Mitte und wird f\u00fcr euch gegen eure Feinde streiten, um euch aus der Gefahr zu erretten.",
    "transcribed_text": "Wenn du gegen deine Feinde zum Krieger ausziehst und sie ist Reiter und Wagen und ein gr\u00f6\u00dferes feindliches Kriegsvolk als du hast so f\u00fcrchte dich nicht vor ihnen denn der Herr dein Gott der dich aus dem Lande \u00c4gypten gef\u00fchrt hat ist mit dir wenn aber die Schlacht nahe bevorsteht so soll der Priester davor das Herz treten und also zum Volk sprechen h\u00f6here Israel ihr liefert heute eine Schlacht gegen eure Feinde euer Herz verzagen nicht f\u00fcrchtet euch nicht Weichert nicht und erschreckt nicht vor ihnen denn der Herr euer Gott ist in eurer Mitte und wird f\u00fcr euch gegen eure Feinde streiten um euch aus der Gefahr zu retten"
}