{
    "chapter": "Lev17",
    "chunk": "004",
    "levenshtein_distance": 18,
    "original_text": "Wenn jemand vom Hause Israel und von den Fremdlingen, die unter ihm weilen, Blut isst, wider eine solche Seele werde ich mein Angesicht wenden, und sie wegtilgen aus ihrem Volke,\ndenn die Seele des Leibes ist im Blute; und ich habe es euch gegeben, damit ihr durch dasselbe auf dem Altare S\u00fchnung schaffet f\u00fcr eure Seelen, und damit das Blut zur S\u00fchne f\u00fcr die Seele gereiche.",
    "transcribed_text": "Wenn jemand vom Hause Israel und von den Fremdlingen die unter ihm weil Blut ist wieder eine solche Seele werde ich mal Angesicht wenden und sie weg tilgen aus ihrem Volke denn die Seele des Leibes ist im blute und ich habe es euch gegeben damit ihr durch das selbe auf dem Altar schafft f\u00fcr eure Seelen und damit das Blut zur S\u00fchne f\u00fcr die Seele gereiche"
}