{
    "chapter": "Offb14",
    "chunk": "003",
    "levenshtein_distance": 2,
    "original_text": "Und ich sah einen anderen Engel mitten durch den Himmel hinfliegen, der das ewige Evangelium hatte, frohe Botschaft den Bewohnern der Erde zu bringen, allen V\u00f6lkern, und St\u00e4mmen, und Zungen und Nationen,\nund er sprach mit starker Stimme: F\u00fcrchtet den Herrn, und gebet ihm die Ehre; denn die Stunde seines Gerichtes ist gekommen. So betet den an, der den Himmel und die Erde, und das Meer und die Wasserquellen geschaffen hat!\nUnd ein zweiter Engel folgte ihm und rief: Gefallen, gefallen ist Babylon, das Gro\u00dfe, welches mit dem Zornwein seiner Unzucht alle V\u00f6lker getr\u00e4nkt hat.",
    "transcribed_text": "Und ich sah einen anderen Engel mitten durch den Himmel hinfliegen der das ewige Evangelium hatte frohe Botschaft den Bewohnern der Erde zu bringen allen V\u00f6lkern und stemmen und Zungen und Nationen und er sprach mit starker Stimme f\u00fcrchtet den Herrn und Gebet ihm die Ehre denn die Stunde seines Gerichtes ist gekommen so betet den an der den Himmel und die Erde und das Meer und die Wasserquellen geschaffen hat und ein zweiter Engel folgte ihm und rief Gefallen gefallen ist Babylon das Gro\u00dfe welches mit dem Zorn Wein seiner Unzucht alle V\u00f6lker getr\u00e4nkt hat"
}