{
    "chapter": "Mi3",
    "chunk": "003",
    "levenshtein_distance": 8,
    "original_text": "Darum soll Nacht \u00fcber euch kommen statt eines Gesichtes und Finsternis statt Wahrsagens, die Sonne soll \u00fcber den Propheten untergehen und der Tag sich \u00fcber ihnen verfinstern.\nDa werden die Seher schamrot werden, die Wahrsager besch\u00e4mt werden und alle werden ihr Angesicht verh\u00fcllen, weil kein Ausspruch von Gott kommt.\nIch aber bin mit der Kraft des Geistes vom Herrn erf\u00fcllt, erf\u00fcllt mit Recht und St\u00e4rke, um Jakob seine Missetat zu verk\u00fcnden und Israel seine S\u00fcnden.",
    "transcribed_text": "Darum soll Nacht \u00fcber euch kommen statt eines Gesichtes und Finsternis statt wahrsagensdie Sonne soll \u00fcber den Propheten untergehen und der Tag sich \u00fcber ihnen f\u00fcr Finstern da werden die sie ja schamrot werden die Wahrsager besch\u00e4mt werden und alle werden ihr Angesicht verh\u00fcllen weil kein Ausspruch von Gott kommt ich aber bin mit der Kraft des Geistes vom Herrn erf\u00fcllt erf\u00fcllt mit Recht und st\u00e4rke um Jakob seine Missetat zu verk\u00fcnden und Israel seine S\u00fcnden"
}