{
    "chapter": "Klgl3",
    "chunk": "008",
    "levenshtein_distance": 17,
    "original_text": "Er biete seine Wange dem dar, der ihn schl\u00e4gt, werde ers\u00e4ttigt mit Schmach. Kaph.\nDenn nicht auf ewig verst\u00f6\u00dft der Herr. Kaph.\nDenn wenn er auch verstie\u00df, so erbarmt er sich doch nach der F\u00fclle seiner Gnaden. Kaph.\nDenn nicht aus Lust beugt er nieder und verst\u00f6\u00dft er die Menschenkinder, Lamed.",
    "transcribed_text": "Er bietet seine Wange dem da der ihn schl\u00e4gt werde er s\u00e4ttigt mit Schmach Kaff der nicht auf ewig verst\u00f6\u00dft der Herr Kaff denn wenn er auch versteht so erbarmt er sich doch nach der F\u00fclle seiner Gnaden Kaff denn nicht aus Lust beugt er nieder und verst\u00f6\u00dft er die Menschen Kinder lahmet"
}