{
    "chapter": "Dtn23",
    "chunk": "004",
    "levenshtein_distance": 15,
    "original_text": "Du sollst au\u00dferhalb des Lagers einen Ort haben, an dem du zur Notdurft der Natur hinausgehst,\nund sollst eine Schaufel am G\u00fcrtel tragen; und wenn du dich dort hinsetzest, sollst du ringsum aufgraben und mit Erde die Ausleerung bedecken,\nvon der du dich erleichtert hast; (denn der Herr, dein Gott, wandelt inmitten des Lagers, um dich zu erretten und dir deine Feinde preiszugeben), und dein Lager soll heilig sein und kein Unflat sich darin finden, damit er dich nicht verlasse.",
    "transcribed_text": "Du sollst au\u00dferhalb des Lagers einen Ort haben an dem du zur Notruf der Natur hinaus gehst und sollst eine Schaufel am G\u00fcrtel tragen und wenn du dich dort hinsetzen sollst du rings um Aufgaben und mit Erde die Auslegung bedecken von der du dich erleichtert hast denn der Herr dein Gott wandelt in mitten des Lagers um dich zu erretten und dir deine Feinde preiszugeben und dein Lager soll heilig sein und kein Unfall hat sich darin finden damit er dich nicht verlasse"
}