{
    "chapter": "1Chr28",
    "chunk": "008",
    "levenshtein_distance": 12,
    "original_text": "F\u00fcr den Altar, auf dem das R\u00e4ucherwerk angez\u00fcndet wird, gab er das lauterste Gold; auch sollte von solchem das Abbild des Gespanns der Cherubim gemacht werden, die ihre Fl\u00fcgel ausbreiten und die Lade des Bundes des Herrn decken.\nAlles, sprach er, ist mir, von der Hand des Herrn geschrieben, zuteil geworden, damit ich alle Werke des Vorbildes verst\u00e4nde.",
    "transcribed_text": "F\u00fcr den Altar auf dem das R\u00e4ucherwerk angez\u00fcndet wird gab er das lauteste Gold auch sollte von solchen das Abbild des Gespann der Cherubim gemacht werden die ihre Fl\u00fcgel ausbreiten und die Lage des Bundes des Herrn alles sprach er ist mir von der Hand des Herrn geschrieben zu teil geworden damit ich alle Werke des Vorbildes verst\u00e4nde"
}