{
    "chapter": "Spr5",
    "chunk": "005",
    "levenshtein_distance": 0,
    "original_text": "Den Gottlosen fangen seine Missetaten und durch die Stricke seiner S\u00fcnden wird er festgehalten.\nEr wird sterben, weil er keine Zucht annahm, und wegen der Gr\u00f6\u00dfe seiner Torheit wird er sich t\u00e4uschen.",
    "transcribed_text": "Den gottlosen fangen seine Missetaten und durch die Stricke seiner S\u00fcnden wird er festgehalten er wird sterben weil er keine Zucht annahm und wegen der Gr\u00f6\u00dfe seiner Torheit wird er sich t\u00e4uschen"
}