{
    "chapter": "Apg19",
    "chunk": "005",
    "levenshtein_distance": 11,
    "original_text": "Es versuchten aber einige von den herumziehenden j\u00fcdischen Teufelsbeschw\u00f6rern \u00fcber diejenigen, welche von b\u00f6sen Geistern besessen waren, den Namen des Herrn Jesus anzurufen, und sagten: Ich beschw\u00f6re euch bei Jesus, welchen Paulus verk\u00fcndet!\nEs waren n\u00e4mlich einige Juden, die sieben S\u00f6hne des j\u00fcdischen Oberpriesters Scevas, die dieses taten.\nDer b\u00f6se Geist aber antwortete, und sprach zu ihnen: Jesus kenne ich, und von Paulus wei\u00df ich; ihr aber, wer seid ihr?\nUnd der Mensch, in welchem der b\u00f6se Geist war, sprang auf sie zu, wurde Herr \u00fcber zwei, und vergewaltigte sie, so dass sie nackt und verwundet aus jenem Hause flohen.",
    "transcribed_text": "Es versuchten aber einige von den herumziehenden j\u00fcdischen Teufelsbeschw\u00f6ren \u00fcber diejenigen welche von b\u00f6sen Geistern besessen waren den Namen des Herrn Jesus anzurufen und sagten ich beschw\u00f6re euch bei Jesus welchen Paulus verk\u00fcndet es war n\u00e4mlich einige Juden die sieben S\u00f6hne des j\u00fcdischen Oberpriester Shavers die dieses Taten der b\u00f6se Geist aber antwortete und sprach zu Ihnen Jesus kenne ich und von Paulus wei\u00df ich ihr aber wer seid ihr und der Mensch in welchen der b\u00f6se Geist war sprang auf sie zu wurde her \u00fcber zwei und vergewaltigte sie so dass sie nackt und verwundert aus jenem Hause flohen"
}